alpyperl/__init__.py
alpyperl/anylogic/__init__.py
alpyperl/anylogic/model/__init__.py
alpyperl/anylogic/model/connector.py
alpyperl/anylogic/model/launcher.py
alpyperl/gym/__init__.py
alpyperl/gym/envs/__init__.py
alpyperl/gym/envs/anylogic_env.py
alpyperl/gym/envs/utils.py
alpyperl/serve/__init__.py
alpyperl/serve/rllib/__init__.py
alpyperl/serve/rllib/binder.py
alpyperl-1.1.2.dist-info/LICENSE
alpyperl-1.1.2.dist-info/METADATA
alpyperl-1.1.2.dist-info/WHEEL
alpyperl-1.1.2.dist-info/top_level.txt
alpyperl-1.1.2.dist-info/RECORD
