Metadata-Version: 2.1
Name: alpyperl
Version: 1.1.2
Summary: An open source library for connecting AnyLogic models with Reinforcement Learning frameworks through OpenAI Gymnasium 
Home-page: https://github.com/MarcEscandell/ALPypeRL
Author: Marc Escandell Mari
Author-email: marcescandellmari@gmail.com
License: Apache License, Version 2.0
Keywords: alpyperl
Platform: UNKNOWN
Requires-Python: >=3.9, <3.11
License-File: LICENSE
Requires-Dist: fastapi ==0.111.0
Requires-Dist: gymnasium ==0.28.1
Requires-Dist: py4j ==0.10.9.7
Requires-Dist: ray[rllib] ==2.31.0
Requires-Dist: tensorflow ==2.16.2
Requires-Dist: torch ==2.3.1
Requires-Dist: uvicorn ==0.30.1
Provides-Extra: docs
Requires-Dist: sphinx-rtd-theme ; extra == 'docs'
